mkx/__init__.py
mkx/attacks/ddos.py
mkx/attacks/exploit.py
mkx/attacks/kill_web_server.py
mkx/cli.py
mkx/core/__init__.py
mkx/core/bytes.py
mkx/core/colors.py
mkx/core/extract_user.py
mkx/core/helps.py
mkx/core/models.py
mkx/core/network.py
mkx/core/settings.py
mkx/discovery/mac_server_discover.py
mkx/discovery/snmp.py
mkx/discovery/upnp.py
mkx-0.2.1.dist-info/METADATA
mkx-0.2.1.dist-info/WHEEL
mkx-0.2.1.dist-info/entry_points.txt
mkx-0.2.1.dist-info/licenses/LICENSE
mkx-0.2.1.dist-info/RECORD
