Metadata-Version: 2.4
Name: mkx
Version: 0.2.1
Summary: CLI for exploring IoT and network devices.
License-File: LICENSE
Author: Henrique Sebastião
Author-email: contato@henriquesebastiao.com
Requires-Python: >=3.13,<4.0
Classifier: Development Status :: 5 - Production/Stable
Classifier: Environment :: Console
Classifier: Intended Audience :: Science/Research
Classifier: Intended Audience :: System Administrators
Classifier: Intended Audience :: Telecommunications Industry
Classifier: License :: OSI Approved :: GNU General Public License v3 (GPLv3)
Classifier: Natural Language :: English
Classifier: Programming Language :: Python :: 3
Classifier: Programming Language :: Python :: 3.13
Classifier: Programming Language :: Python :: 3.14
Classifier: Topic :: Internet
Classifier: Topic :: Security
Requires-Dist: httpx (>=0.28.1,<0.29.0)
Requires-Dist: prompt-toolkit (>=3.0.52,<4.0.0)
Requires-Dist: pydantic (>=2.12.5,<3.0.0)
Requires-Dist: pysnmp (>=7.1.22,<8.0.0)
Requires-Dist: typer (>=0.20,<0.22)
Requires-Dist: upnpy (>=1.1.8,<2.0.0)
Project-URL: Bug Tracker, https://github.com/henriquesebastiao/mkx/issues
Project-URL: Repository, https://github.com/henriquesebastiao/mkx
